valer.core-1.3.5rc13-nspkg.pth
bika/lims/__init__.py
bika/lims/alphanumber.py
bika/lims/barcode.py
bika/lims/config.py
bika/lims/configure.zcml
bika/lims/decorators.py
bika/lims/fields.py
bika/lims/idserver.py
bika/lims/numbergenerator.py
bika/lims/overrides.zcml
bika/lims/permissions.py
bika/lims/permissions.txt
bika/lims/permissions.zcml
bika/lims/profiles.zcml
bika/lims/setuphandlers.py
bika/lims/testing.py
bika/lims/validators.py
bika/lims/version.txt
bika/lims/adapters/__init__.py
bika/lims/adapters/addsample.py
bika/lims/adapters/configure.zcml
bika/lims/adapters/dynamicresultsrange.py
bika/lims/adapters/referencewidgetvocabulary.py
bika/lims/adapters/stickers.py
bika/lims/adapters/widgetvisibility.py
bika/lims/api/__init__.py
bika/lims/api/analysis.py
bika/lims/api/analysisservice.py
bika/lims/api/mail.py
bika/lims/api/security.py
bika/lims/api/snapshot.py
bika/lims/api/user.py
bika/lims/browser/__init__.py
bika/lims/browser/accreditation.py
bika/lims/browser/analysis.py
bika/lims/browser/analysis.zcml
bika/lims/browser/analysisprofile.py
bika/lims/browser/analysisprofile.zcml
bika/lims/browser/analysisreport.py
bika/lims/browser/analysisreport.zcml
bika/lims/browser/analysisservice.py
bika/lims/browser/analysisservice.zcml
bika/lims/browser/artemplate.py
bika/lims/browser/artemplate.zcml
bika/lims/browser/attachment.py
bika/lims/browser/attachment.zcml
bika/lims/browser/auditlog.py
bika/lims/browser/auditlog.zcml
bika/lims/browser/batchfolder.py
bika/lims/browser/batchfolder.zcml
bika/lims/browser/bika_listing.py
bika/lims/browser/calcs.py
bika/lims/browser/calcs.zcml
bika/lims/browser/clientfolder.py
bika/lims/browser/clientfolder.zcml
bika/lims/browser/configure.zcml
bika/lims/browser/contact.py
bika/lims/browser/contact.zcml
bika/lims/browser/contentmenu.py
bika/lims/browser/contentmenu.zcml
bika/lims/browser/controlpanel.py
bika/lims/browser/controlpanel.zcml
valer.core-1.3.5rc13.dist-info/DESCRIPTION.rst
valer.core-1.3.5rc13.dist-info/METADATA
valer.core-1.3.5rc13.dist-info/RECORD
valer.core-1.3.5rc13.dist-info/WHEEL
valer.core-1.3.5rc13.dist-info/entry_points.txt
valer.core-1.3.5rc13.dist-info/metadata.json
valer.core-1.3.5rc13.dist-info/namespace_packages.txt
valer.core-1.3.5rc13.dist-info/top_level.txt
