Metadata-Version: 2.0
Name: valer.core
Version: 1.3.5rc13
Summary: Valer LIMS Core
Home-page: https://github.com/valeriozhang/senaite.core
Author: Valer Group LLC
Author-email: valerio.zhang@valer.us
License: GPLv2
Keywords: senaite,lims,opensource,Valer
Platform: UNKNOWN
Classifier: Development Status :: 5 - Production/Stable
Classifier: Environment :: Web Environment
Classifier: Framework :: Plone
Classifier: Framework :: Zope2
Classifier: Programming Language :: Python
Provides-Extra: test
Requires-Dist: CairoSVG (==1.0.20)
Requires-Dist: Pillow (<7.0.0)
Requires-Dist: Products.ATExtensions (>=1.1a3)
Requires-Dist: Products.CMFEditions
Requires-Dist: Products.DataGridField
Requires-Dist: Products.TextIndexNG3
Requires-Dist: Products.TinyMCE
Requires-Dist: WeasyPrint (==0.42.3)
Requires-Dist: cairocffi (<1.0.0)
Requires-Dist: collective.indexing
Requires-Dist: collective.js.jqueryui
Requires-Dist: collective.monkeypatcher
Requires-Dist: collective.progressbar
Requires-Dist: cssselect2 (<0.3.0)
Requires-Dist: five.pt (==2.2.4)
Requires-Dist: jarn.jsi18n
Requires-Dist: magnitude
Requires-Dist: more-itertools (<6.0.0)
Requires-Dist: openpyxl (==1.5.8)
Requires-Dist: plone.api
Requires-Dist: plone.app.dexterity
Requires-Dist: plone.app.iterate
Requires-Dist: plone.app.referenceablebehavior
Requires-Dist: plone.app.relationfield
Requires-Dist: plone.app.z3cform
Requires-Dist: plone.jsonapi.core
Requires-Dist: plone.resource
Requires-Dist: plone.subrequest
Requires-Dist: setuptools
Requires-Dist: simplejson
Requires-Dist: six
Requires-Dist: soupsieve (<2.0.0)
Requires-Dist: tinycss2 (<1.0.0)
Requires-Dist: valer.core.listing (>=1.5.3rc11)
Requires-Dist: valer.core.spotlight (>=1.0.3rc11)
Requires-Dist: valer.core.supermodel (>=1.2.4rc11)
Requires-Dist: valer.impress (>=1.2.4rc11)
Requires-Dist: z3c.jbot
Requires-Dist: zopyx.txng3.ext (==3.4.0)
Provides-Extra: test
Requires-Dist: plone.app.testing; extra == 'test'
Requires-Dist: unittest2; extra == 'test'
